SLIP/SLIP.py
SLIP/__init__.py
SLIP-20171205.dist-info/DESCRIPTION.rst
SLIP-20171205.dist-info/METADATA
SLIP-20171205.dist-info/RECORD
SLIP-20171205.dist-info/WHEEL
SLIP-20171205.dist-info/metadata.json
SLIP-20171205.dist-info/top_level.txt
